Workbook

Sheet ダッシュボード
A1: ぺいほーむ 事業推進管理シート
A2: 最終更新: 2026-03-22
A4: 進捗サマリー
A5: カテゴリ | B5: 全タスク数 | C5: 完了 | D5: 進行中 | E5: 未着手 | F5: 完了率 | G5: 担当
A6: 事業戦略・収益化 | B6: =COUNTIF('Todo詳細'!B:B,"収益")+COUNTIF('Todo詳細'!B:B,"戦略") | C6: =COUNTIFS('Todo詳細'!B:B,"収益",'Todo詳細'!K:K,"完了")+COUNTIFS('Todo詳細'!B:B,"戦略",'Todo詳細'!K:K,"完了") | D6: =COUNTIFS('Todo詳細'!B:B,"収益",'Todo詳細'!K:K,"進行中")+COUNTIFS('Todo詳細'!B:B,"戦略",'Todo詳細'!K:K,"進行中") | E6: =COUNTIFS('Todo詳細'!B:B,"収益",'Todo詳細'!K:K,"未着手")+COUNTIFS('Todo詳細'!B:B,"戦略",'Todo詳細'!K:K,"未着手") | F6: =IF(B6=0,"-",C6/B6) | G6: 経営
A7: 営業・アライアンス | B7: =COUNTIF('Todo詳細'!B:B,"営業") | C7: =COUNTIFS('Todo詳細'!B:B,"営業",'Todo詳細'!K:K,"完了") | D7: =COUNTIFS('Todo詳細'!B:B,"営業",'Todo詳細'!K:K,"進行中") | E7: =COUNTIFS('Todo詳細'!B:B,"営業",'Todo詳細'!K:K,"未着手") | F7: =IF(B7=0,"-",C7/B7) | G7: 経営/営業
A8: 掲載品質・リライト | B8: =COUNTIF('Todo詳細'!B:B,"品質") | C8: =COUNTIFS('Todo詳細'!B:B,"品質",'Todo詳細'!K:K,"完了") | D8: =COUNTIFS('Todo詳細'!B:B,"品質",'Todo詳細'!K:K,"進行中") | E8: =COUNTIFS('Todo詳細'!B:B,"品質",'Todo詳細'!K:K,"未着手") | F8: =IF(B8=0,"-",C8/B8) | G8: コンテンツ
A9: 集客・マーケティング | B9: =COUNTIF('Todo詳細'!B:B,"集客") | C9: =COUNTIFS('Todo詳細'!B:B,"集客",'Todo詳細'!K:K,"完了") | D9: =COUNTIFS('Todo詳細'!B:B,"集客",'Todo詳細'!K:K,"進行中") | E9: =COUNTIFS('Todo詳細'!B:B,"集客",'Todo詳細'!K:K,"未着手") | F9: =IF(B9=0,"-",C9/B9) | G9: マーケ
A10: オペレーション | B10: =COUNTIF('Todo詳細'!B:B,"オペ") | C10: =COUNTIFS('Todo詳細'!B:B,"オペ",'Todo詳細'!K:K,"完了") | D10: =COUNTIFS('Todo詳細'!B:B,"オペ",'Todo詳細'!K:K,"進行中") | E10: =COUNTIFS('Todo詳細'!B:B,"オペ",'Todo詳細'!K:K,"未着手") | F10: =IF(B10=0,"-",C10/B10) | G10: CS/経営
A11: KPI・計測 | B11: =COUNTIF('Todo詳細'!B:B,"計測")+COUNTIF('Todo詳細'!B:B,"データ")+COUNTIF('Todo詳細'!B:B,"CV") | C11: =COUNTIFS('Todo詳細'!B:B,"計測",'Todo詳細'!K:K,"完了")+COUNTIFS('Todo詳細'!B:B,"データ",'Todo詳細'!K:K,"完了")+COUNTIFS('Todo詳細'!B:B,"CV",'Todo詳細'!K:K,"完了") | D11: =COUNTIFS('Todo詳細'!B:B,"計測",'Todo詳細'!K:K,"進行中")+COUNTIFS('Todo詳細'!B:B,"データ",'Todo詳細'!K:K,"進行中")+COUNTIFS('Todo詳細'!B:B,"CV",'Todo詳細'!K:K,"進行中") | E11: =COUNTIFS('Todo詳細'!B:B,"計測",'Todo詳細'!K:K,"未着手")+COUNTIFS('Todo詳細'!B:B,"データ",'Todo詳細'!K:K,"未着手")+COUNTIFS('Todo詳細'!B:B,"CV",'Todo詳細'!K:K,"未着手") | F11: =IF(B11=0,"-",C11/B11) | G11: PM
A12: コンテンツ制作 | B12: =COUNTIF('Todo詳細'!B:B,"コンテンツ") | C12: =COUNTIFS('Todo詳細'!B:B,"コンテンツ",'Todo詳細'!K:K,"完了") | D12: =COUNTIFS('Todo詳細'!B:B,"コンテンツ",'Todo詳細'!K:K,"進行中") | E12: =COUNTIFS('Todo詳細'!B:B,"コンテンツ",'Todo詳細'!K:K,"未着手") | F12: =IF(B12=0,"-",C12/B12) | G12: コンテンツ
A13: 合計 | B13: =SUM(B6:B12) | C13: =SUM(C6:C12) | D13: =SUM(D6:D12) | E13: =SUM(E6:E12) | F13: =IF(B13=0,"-",C13/B13) | G13: -
A15: 直近マイルストーン
A16: マイルストーン | B16: 目標日 | C16: 状態 | D16: 担当 | E16: 備考
A17: 営業提案書 完成 | B17: 2026-04-01 | C17: 完了 | D17: 経営
A18: GA4計測 稼働開始 | B18: 2026-04-01 | C18: 未着手 | D18: PM/エンジニア
A19: 初期パートナー1社 獲得 | B19: 2026-04-15 | C19: 未着手 | D19: 経営/営業 | E19: 最重要
A20: 掲載品質監査 完了 | B20: 2026-04-07 | C20: 完了 | D20: コンテンツ
A21: 週次KPIレポート 開始 | B21: 2026-04-07 | C21: 完了 | D21: PM
A22: パートナー3社 達成 | B22: 2026-05-15 | C22: 未着手 | D22: 営業
A23: 月次売上 発生 | B23: 2026-06-15 | C23: 未着手 | D23: 経営

Sheet ガントチャート
A1: ID | B1: 担当 | C1: カテゴリ | D1: タスク名 | E1: 開始日 | F1: 終了日 | G1: 日数 | H1: ステータス | I1: 進捗% | J1: W1 03/24 | K1: W2 03/31 | L1: W3 04/07 | M1: W4 04/14 | N1: W5 04/21 | O1: W6 04/28 | P1: W7 05/05 | Q1: W8 05/12 | R1: W9 05/19 | S1: W10 05/26 | T1: W11 06/02 | U1: W12 06/09
A2: 【Month 1: 基盤固め・営業開始】
A3: T-06 | B3: 経営 | C3: 戦略 | D3: エレベーターピッチ作成 | E3: 03/24 | F3: 03/28 | G3: 5 | H3: 完了 | I3: 1
A4: T-07 | B4: 経営 | C4: 営業 | D4: 営業提案書 初稿作成 | E4: 03/24 | F4: 04/04 | G4: 10 | H4: 完了 | I4: 1
A5: T-25 | B5: コンテンツ | C5: 品質 | D5: 掲載基準・フォーマット策定 | E5: 03/24 | F5: 03/31 | G5: 7 | H5: 完了 | I5: 1
A6: T-09 | B6: PM | C6: 計測 | D6: GA4セットアップ | E6: 03/24 | F6: 03/31 | G6: 7 | H6: 未着手 | I6: 0
A7: T-26 | B7: コンテンツ | C7: 品質 | D7: 全ページ文言監査 | E7: 03/24 | F7: 04/07 | G7: 14 | H7: 完了 | I7: 1
A8: T-32 | B8: 経営 | C8: オペ | D8: 問い合わせ対応フロー設計 | E8: 03/24 | F8: 04/04 | G8: 10 | H8: 完了 | I8: 1
A9: T-17 | B9: 経営 | C9: 営業 | D9: 営業提案フロー設計 | E9: 03/31 | F9: 04/07 | G9: 7 | H9: 完了 | I9: 1
A10: T-35 | B10: 経営 | C10: 収益 | D10: 料金プラン確定 | E10: 03/31 | F10: 04/07 | G10: 7 | H10: 未着手 | I10: 0
A11: T-27 | B11: コンテンツ | C11: 品質 | D11: 再ヒアリング項目整理 | E11: 03/31 | F11: 04/07 | G11: 7 | H11: 完了 | I11: 1
A12: T-04 | B12: 経営 | C12: 戦略 | D12: ペルソナ3パターン作成 | E12: 03/31 | F12: 04/07 | G12: 7 | H12: 完了 | I12: 1
A13: T-02 | B13: PM | C13: 計測 | D13: KPI定義・計測開始 | E13: 03/31 | F13: 04/07 | G13: 7 | H13: 未着手 | I13: 0
A14: T-40 | B14: 経営 | C14: 戦略 | D14: 四半期マイルストーン設定 | E14: 03/31 | F14: 04/07 | G14: 7 | H14: 未着手 | I14: 0
... A24: T-13 | B24: PM | C24: 計測 | D24: CV率計測・分析開始 | E24: 04/14 | F24: 04/21 | G24: 7 | H24: 未着手 | I24: 0
A25: 【Month 2: 拡大準備・コンテンツ充実】
A26: T-05 | B26: 営業 | C26: 戦略 | D26: 工務店ターゲットリスト作成 | E26: 04/21 | F26: 05/02 | G26: 10 | H26: 未着手 | I26: 0
A27: T-11 | B27: コンテンツ | C27: 集客 | D27: SEO記事制作(月3本) | E27: 04/21 | F27: 05/15 | G27: 24 | H27: 完了 | I27: 1
A28: T-12 | B28: マーケ | C28: 集客 | D28: LINE公式運用開始 | E28: 04/21 | F28: 05/02 | G28: 10 | H28: 未着手 | I28: 0
A29: T-20 | B29: 営業 | C29: 営業 | D29: 新規工務店アプローチ(月5社) | E29: 04/28 | F29: 05/22 | G29: 24 | H29: 未着手 | I29: 0
A30: T-22 | B30: コンテンツ | C30: コンテンツ | D30: 月次コンテンツカレンダー作成 | E30: 04/21 | F30: 04/28 | G30: 7 | H30: 完了 | I30: 1
A31: T-30 | B31: コンテンツ | C31: 品質 | D31: SEOメタデータ一括入力 | E31: 04/21 | F31: 05/02 | G31: 10 | H31: 完了 | I31: 1
A32: T-31 | B32: コンテンツ | C32: 品質 | D32: マガジン表紙画像制作 | E32: 04/28 | F32: 05/15 | G32: 17 | H32: 未着手 | I32: 0
A33: T-42 | B33: コンテンツ | C33: 品質 | D33: 構造化データ入力 | E33: 05/04 | F33: 05/22 | G33: 18 | H33: 未着手 | I33: 0
A34: T-39 | B34: PM | C34: 計測 | D34: 月次レビュー会議開始 | E34: 05/04 | F34: 05/11 | G34: 7 | H34: 完了 | I34: 1
A35: 【Month 3: 検証・改善・次フェーズ準備】
A36: T-01 | B36: 経営 | C36: 収益 | D36: 収益モデル初期検証 | E36: 05/18 | F36: 06/05 | G36: 18 | H36: 未着手 | I36: 0
A37: T-03 | B37: 経営 | C37: 戦略 | D37: 月次P/L作成 | E37: 05/18 | F37: 05/25 | G37: 7 | H37: 完了 | I37: 1
A38: T-14 | B38: PM | C38: CV | D38: フォーム離脱率分析・改善 | E38: 05/18 | F38: 06/01 | G38: 14 | H38: 未着手 | I38: 0
A39: T-15 | B39: PM | C39: データ | D39: データ活用ロードマップ確定 | E39: 05/25 | F39: 06/08 | G39: 14 | H39: 完了 | I39: 1
A40: T-16 | B40: PM | C40: データ | D40: 月次データレポート作成 | E40: 06/01 | F40: 06/15 | G40: 14 | H40: 完了 | I40: 1
A41: T-23 | B41: コンテンツ | C41: コンテンツ | D41: 比較コンテンツ制作 | E41: 05/18 | F41: 06/15 | G41: 28 | H41: 完了 | I41: 1
A42: T-24 | B42: コンテンツ | C42: コンテンツ | D42: AIチャット用FAQ整理 | E42: 05/25 | F42: 06/08 | G42: 14 | H42: 完了 | I42: 1
A43: T-41 | B43: 経営 | C43: 戦略 | D43: 年間事業計画策定 | E43: 06/01 | F43: 06/15 | G43: 14 | H43: 未着手 | I43: 0
A44: T-34 | B44: 経営 | C44: オペ | D44: SLA設定 | E44: 06/01 | F44: 06/08 | G44: 7 | H44: 完了 | I44: 1

Sheet 担当別Todo
A1: 担当 | B1: ID | C1: タスク名 | D1: カテゴリ | E1: 期限 | F1: 優先度 | G1: ステータス | H1: 次のアクション | I1: 備考
A3: 経営 | B3: T-06 | C3: エレベーターピッチ作成 | D3: 戦略 | E3: 03/28 | F3: 高 | G3: 完了 | H3: AIで草案3パターン生成→選定
A4: 経営 | B4: T-07 | C4: 営業提案書 初稿 | D4: 営業 | E4: 04/04 | F4: 高 | G4: 完了 | H4: AIで構成案作成→レビュー
A5: 経営 | B5: T-35 | C5: 料金プラン確定 | D5: 収益 | E5: 04/07 | F5: 高 | G5: 未着手 | H5: 競合調査→3プラン価格決定
A6: 経営 | B6: T-17 | C6: 営業フロー設計 | D6: 営業 | E6: 04/07 | F6: 高 | G6: 完了 | H6: AIでフロー草案→調整
A7: 経営 | B7: T-32 | C7: 問い合わせ対応フロー | D7: オペ | E7: 04/04 | F7: 高 | G7: 完了 | H7: AIでフロー草案→確定
A8: 経営 | B8: T-19 | C8: 既存取材先への提案 | D8: 営業 | E8: 04/18 | F8: 高 | G8: 未着手 | H8: アポ取得→提案書持参→交渉
A9: 経営 | B9: T-36 | C9: 初期パートナー1社獲得 | D9: 収益 | E9: 04/25 | F9: 高 | G9: 未着手 | H9: T-19の結果→契約締結 | I9: 最重要
A10: 経営 | B10: T-40 | C10: 四半期マイルストーン | D10: 戦略 | E10: 04/07 | F10: 高 | G10: 未着手 | H10: Q2/Q3/Q4目標値設定
A11: 経営 | B11: T-08 | C11: 料金プラン確定 | D11: 収益 | E11: 04/07 | F11: 高 | G11: 未着手 | H11: 3プランの最終価格決定 | I11: 経営専権
A13: 営業 | B13: T-28 | C13: 工務店再ヒアリング(1-3社) | D13: 品質 | E13: 04/21 | F13: 高 | G13: 未着手 | H13: 質問シート(T-27)→訪問実施
A14: 営業 | B14: T-05 | C14: ターゲットリスト50社 | D14: 戦略 | E14: 05/02 | F14: 中 | G14: 未着手 | H14: AI補助でリスト収集→人間確認
A15: 営業 | B15: T-20 | C15: 新規アプローチ(月5社) | D15: 営業 | E15: 05/22 | F15: 中 | G15: 未着手 | H15: リスト→アポ→提案
A16: 営業 | B16: T-18 | C16: 契約書テンプレート | D16: 営業 | E16: 04/14 | F16: 高 | G16: 完了 | H16: AIで草案→法務確認
A18: PM | B18: T-09 | C18: GA4セットアップ | D18: 計測 | E18: 03/31 | F18: 高 | G18: 未着手 | H18: エンジニアと連携→設定完了
A19: PM | B19: T-02 | C19: KPI定義・計測開始 | D19: 計測 | E19: 04/07 | F19: 高 | G19: 未着手 | H19: 5項目選定→計測設計→稼働
A20: PM | B20: T-38 | C20: 週次KPIレポート開始 | D20: 計測 | E20: 04/21 | F20: 高 | G20: 完了 | H20: テンプレート作成→毎週実施
A21: PM | B21: T-13 | C21: CV率計測開始 | D21: CV | E21: 04/21 | F21: 中 | G21: 未着手 | H21: GA4イベント→レポート化
A22: PM | B22: T-15 | C22: データ活用ロードマップ | D22: データ | E22: 06/08 | F22: 中 | G22: 完了 | H22: AIでたたき台→経営判断
A24: マーケ | B24: T-10 | C24: YouTube概要欄CTA | D24: 集客 | E24: 04/14 | F24: 高 | G24: 完了 | H24: 全動画にWeb導線テンプレ適用
A25: マーケ | B25: T-12 | C25: LINE公式運用開始 | D25: 集客 | E25: 05/02 | F25: 中 | G25: 未着手 | H25: 開設→友だち追加導線→配信開始
A27: コンテンツ | B27: T-25 | C27: 掲載基準策定 | D27: 品質 | E27: 03/31 | F27: 高 | G27: 完了 | H27: AIでたたき台→レビュー→確定
... A31: コンテンツ | B31: T-29 | C31: リライト実施(5件) | D31: 品質 | E31: 04/25 | F31: 中 | G31: 未着手 | H31: AIで草案→人間レビュー→公開
A32: コンテンツ | B32: T-30 | C32: SEOメタデータ一括入力 | D32: 品質 | E32: 05/02 | F32: 中 | G32: 完了 | H32: AI一括生成(80件)→レビュー | I32: AI自動化◎
A33: コンテンツ | B33: T-11 | C33: SEO記事制作(月3本) | D33: 集客 | E33: 05/15 | F33: 中 | G33: 完了 | H33: AI下書き→事実確認→公開
A34: コンテンツ | B34: T-24 | C34: FAQ整理(50問) | D34: コンテンツ | E34: 06/08 | F34: 中 | G34: 完了 | H34: AI一括生成→精査→RAG投入 | I34: AI自動化◎

Sheet Todo詳細
A1: ID | B1: カテゴリ | C1: タスク名 | D1: 背景/目的 | E1: 具体的アクション | F1: 成果物 | G1: 担当 | H1: 優先度 | I1: 開始日 | J1: 期限 | K1: ステータス | L1: 進捗% | M1: 自動化 | N1: メモ | O1: 追加日
A2: T-01 | B2: 収益 | C2: 収益モデル初期検証 | D2: 全収益モデルが未検証 | E2: 反響課金で最初の1件を有料実施→単価・オペレーション検証 | F2: 検証結果レポート | G2: 経営 | H2: 高 | I2: 05/18 | J2: 06/05 | K2: 未着手 | L2: 0 | M2: D | O2: 2026-03-22
A3: T-02 | B3: 計測 | C3: KPI定義・計測開始 | D3: KPIが定義済みだが計測未開始 | E3: 主要5項目選定→計測設計→週次追跡 | F3: KPI一覧・計測設計書 | G3: PM | H3: 高 | I3: 03/31 | J3: 04/07 | K3: 未着手 | L3: 0 | M3: B | O3: 2026-03-22
A4: T-03 | B4: 戦略 | C4: 月次P/L作成 | D4: 収支が見える化されていない | E4: 月次の収入支出を整理→損益把握 | F4: P/Lテンプレート | G4: 経営 | H4: 高 | I4: 05/18 | J4: 05/25 | K4: 完了 | L4: 1 | M4: B | O4: 2026-03-22
A5: T-04 | B5: 戦略 | C5: ペルソナ3パターン作成 | D5: YouTube実データはあるがペルソナ未言語化 | E5: 55-64歳/45-54歳/35-44歳の3パターン具体化 | F5: ペルソナカード3枚 | G5: 経営 | H5: 高 | I5: 03/31 | J5: 04/07 | K5: 完了 | L5: 1 | M5: B | O5: 2026-03-22
A6: T-05 | B6: 戦略 | C6: 工務店ターゲットリスト50社 | D6: 営業先リストが存在しない | E6: 鹿児島・福岡中心に50社リスト作成 | F6: ターゲットリスト | G6: 営業 | H6: 中 | I6: 04/21 | J6: 05/02 | K6: 未着手 | L6: 0 | M6: C | O6: 2026-03-22
A7: T-06 | B7: 戦略 | C7: エレベーターピッチ作成 | D7: 30秒で事業を説明できる言葉がない | E7: 消費者向け/工務店向け2パターン | F7: ピッチ文書 | G7: 経営 | H7: 高 | I7: 03/24 | J7: 03/28 | K7: 完了 | L7: 1 | M7: B | O7: 2026-03-22
A8: T-07 | B8: 営業 | C8: 営業提案書作成 | D8: 営業資料がない | E8: 10-15P提案書(事業概要/プラン/料金) | F8: 提案書PDF | G8: 経営 | H8: 高 | I8: 03/24 | J8: 04/04 | K8: 完了 | L8: 1 | M8: B | O8: 2026-03-22
A9: T-08 | B9: 収益 | C9: 料金プラン確定 | D9: 料金が仮設定 | E9: 3プランの価格・内容を確定 | F9: 料金プラン表 | G9: 経営 | H9: 高 | I9: 03/31 | J9: 04/07 | K9: 未着手 | L9: 0 | M9: D | O9: 2026-03-22
A10: T-09 | B10: 計測 | C10: GA4セットアップ | D10: Webアクセスデータが取れていない | E10: GA4初期設定→主要イベント計測開始 | F10: GA4稼働 | G10: PM | H10: 高 | I10: 03/24 | J10: 03/31 | K10: 未着手 | L10: 0 | M10: C | O10: 2026-03-22
A11: T-10 | B11: 集客 | C11: YouTube概要欄CTA最適化 | D11: YouTube→Web送客導線が未最適化 | E11: 全動画概要欄にURL+CTA追加 | F11: 概要欄テンプレート | G11: マーケ | H11: 高 | I11: 04/07 | J11: 04/14 | K11: 完了 | L11: 1 | M11: B | O11: 2026-03-22
A12: T-11 | B12: 集客 | C12: SEO記事追加(月3本) | D12: 検索流入が未開拓 | E12: キーワード調査→構成→下書き→公開 | F12: 記事3本/月 | G12: コンテンツ | H12: 中 | I12: 04/21 | J12: 05/15 | K12: 完了 | L12: 1 | M12: B | O12: 2026-03-22
A13: T-12 | B13: 集客 | C13: LINE公式運用開始 | D13: LINEでのCRM未稼働 | E13: 開設→友だち追加導線→週次配信 | F13: LINE運用計画 | G13: マーケ | H13: 中 | I13: 04/21 | J13: 05/02 | K13: 未着手 | L13: 0 | M13: C | O13: 2026-03-22
... A45: T-44 | B45: 品質 | C45: 物件ページ画像整備 | D45: 写真がプレースホルダー | E45: 実写真撮影/収集→差し替え | F45: 物件写真 | G45: コンテンツ | H45: 中 | I45: 05/18 | J45: 06/15 | K45: 未着手 | L45: 0 | M45: D | O45: 2026-03-22
A46: T-45
A47: T-46
A48: T-47
A49: T-48
A50: T-49
A51: T-50
A52: T-51
A53: T-52
A54: T-53
A55: T-54

Sheet 追加Todo受付
A1: 追加日 | B1: 起票者 | C1: カテゴリ | D1: タスク名 | E1: 背景/目的 | F1: 優先度(仮) | G1: 希望期限 | H1: 担当(案) | I1: 承認 | J1: Todo一覧に反映 | K1: 備考

Sheet 使い方ガイド
A1: 事業管理 使い方ガイド
A2: ぺいほーむ事業全体のタスク管理・進捗管理ファイルです。毎週のKPIミーティングとタスク確認に使用します。
A4: シート名 | B4: 用途・使い方 | C4: 更新頻度
A5: ダッシュボード | B5: 全体の進捗サマリー。カテゴリ別の完了率が自動計算される。毎週月曜に確認 | C5: 週次
A6: ガントチャート | B6: 12週間のタスクスケジュール。オレンジバーが稼働週。ステータスと進捗%を毎週更新 | C6: 週次
A7: 担当別Todo | B7: 経営/営業/PM/マーケ/コンテンツの担当ごとにタスクを確認。「次のアクション」列が最重要 | C7: 週次
A8: Todo詳細 | B8: 全44タスクの詳細情報。追加Todoは下部の空行に追記可能（T-45以降） | C8: 随時
A9: 追加Todo受付 | B9: 新しいTodoが発生したらここに起票→経営承認→Todo詳細に転記 | C9: 随時
A11: 関連ファイル
A12: payhome_project_management.xlsx | B12: 事業全体のTodo・ガントチャート・進捗管理
A13: payhome_sales.xlsx | B13: 営業提案フロー・メールDM・工務店ヒアリング・ペルソナ
A14: payhome_content.xlsx | B14: コンテンツカレンダー・YouTube戦略・動画企画・掲載監査
A15: payhome_finance_kpi.xlsx | B15: 月次P/L・KPIレポート・請求・データ活用ロードマップ
A16: payhome_sales_deck.pptx | B16: 営業提案書（PowerPoint）
A17: contract_template.docx | B17: 契約書テンプレート（Word）
A18: listing_standards.docx | B18: 掲載基準書・品質管理ガイド（Word）
A19: operations_manual.docx | B19: オペレーションマニュアル（Word）
